{"StreamConfig":{},"State":{"Running":false,"Paused":false,"Restarting":false,"OOMKilled":false,"RemovalInProgress":false,"Dead":false,"Pid":0,"ExitCode":137,"Error":"","StartedAt":"2020-10-05T21:04:13.19948772Z","FinishedAt":"2020-10-05T21:06:24.85534917Z","Health":null},"ID":"7ba9f6c36d31050f3cc8bd13085f1c626643d9ac0b48e8414d7016e55ae2cb6d","Created":"2020-10-05T21:04:12.30898374Z","Managed":false,"Path":"/bin/sh","Args":["-c","python3 Main.py"],"Config":{"Hostname":"7ba9f6c36d31","Domainname":"","User":"","AttachStdin":false,"AttachStdout":false,"AttachStderr":false,"ExposedPorts":{"5050/tcp":{}},"Tty":false,"OpenStdin":false,"StdinOnce":false,"Env":["PATH=/usr/local/sbin:/usr/local/bin:/usr/sbin:/usr/bin:/sbin:/bin","SERV_PORT=5050"],"Cmd":["/bin/sh","-c","python3 Main.py"],"Image":"wserv:latest","Volumes":null,"WorkingDir":"","Entrypoint":null,"OnBuild":null,"Labels":{}},"Image":"sha256:653469d5570ea1a75feea05982ac6c10d176c8dfdfec517b2b98dd676842a8c2","NetworkSettings":{"Bridge":"","SandboxID":"ad4a0f42f837ede56074c3ac21d7e7f4426d7c03211c0c8e43d6bed5bdf3c37b","HairpinMode":false,"LinkLocalIPv6Address":"","LinkLocalIPv6PrefixLen":0,"Networks":{"bridge":{"IPAMConfig":null,"Links":null,"Aliases":null,"NetworkID":"7c6348fba76b39b19b57806fc18b1bcd5f7bccd68e7ea9970aabc1a433bade00","EndpointID":"","Gateway":"","IPAddress":"","IPPrefixLen":0,"IPv6Gateway":"","GlobalIPv6Address":"","GlobalIPv6PrefixLen":0,"MacAddress":"","DriverOpts":null,"IPAMOperational":false}},"Service":null,"Ports":null,"SandboxKey":"/var/run/docker/netns/ad4a0f42f837","SecondaryIPAddresses":null,"SecondaryIPv6Addresses":null,"IsAnonymousEndpoint":true,"HasSwarmEndpoint":false},"LogPath":"/var/lib/docker/containers/7ba9f6c36d31050f3cc8bd13085f1c626643d9ac0b48e8414d7016e55ae2cb6d/7ba9f6c36d31050f3cc8bd13085f1c626643d9ac0b48e8414d7016e55ae2cb6d-json.log","Name":"/sharp_neumann","Driver":"overlay2","OS":"linux","MountLabel":"","ProcessLabel":"","RestartCount":0,"HasBeenStartedBefore":true,"HasBeenManuallyStopped":true,"MountPoints":{},"SecretReferences":null,"ConfigReferences":null,"AppArmorProfile":"","HostnamePath":"/var/lib/docker/containers/7ba9f6c36d31050f3cc8bd13085f1c626643d9ac0b48e8414d7016e55ae2cb6d/hostname","HostsPath":"/var/lib/docker/containers/7ba9f6c36d31050f3cc8bd13085f1c626643d9ac0b48e8414d7016e55ae2cb6d/hosts","ShmPath":"","ResolvConfPath":"/var/lib/docker/containers/7ba9f6c36d31050f3cc8bd13085f1c626643d9ac0b48e8414d7016e55ae2cb6d/resolv.conf","SeccompProfile":"","NoNewPrivileges":false}
